tw_textforge/__init__.py
tw_textforge/utils.py
tw_textforge/agent/__init__.py
tw_textforge/agent/ai_model.py
tw_textforge/agent/printer.py
tw_textforge/agent/GSAT/__init__.py
tw_textforge/agent/GSAT/chinese.py
tw_textforge/agent/general/__init__.py
tw_textforge/agent/general/dual_agent_graph.py
tw_textforge/agent/general/multi_agnet_graph.py
tw_textforge/agent/general/single_agent_graph.py
tw_textforge/config/__init__.py
tw_textforge/config/settings.py
tw_textforge/dataset/__init__.py
tw_textforge/dataset/loader.py
tw_textforge/prompt/__init__.py
tw_textforge/prompt/GSAT/chinese.py
tw_textforge/prompt/general/__init__.py
tw_textforge/prompt/general/general_prompt.py
tw_textforge/sdk/__init__.py
tw_textforge/sdk/GSAT/Chinese.py
tw_textforge-0.0.4.dist-info/licenses/LICENSE
tw_textforge-0.0.4.dist-info/METADATA
tw_textforge-0.0.4.dist-info/WHEEL
tw_textforge-0.0.4.dist-info/top_level.txt
tw_textforge-0.0.4.dist-info/RECORD
