Metadata-Version: 2.4
Name: tw_textforge
Version: 0.0.4
Author-email: Xuan‑You Lin <a0985821880@gmail.com>
Maintainer-email: Xuan‑You Lin <a0985821880@gmail.com>
License-Expression: Apache-2.0
Requires-Python: <3.13,>3.10
License-File: LICENSE
Requires-Dist: setuptools
Requires-Dist: ipykernel
Requires-Dist: ipywidgets
Requires-Dist: nest_asyncio
Requires-Dist: jupyterlab_widgets
Requires-Dist: pydantic
Requires-Dist: python-dotenv
Requires-Dist: huggingface_hub[cli]
Requires-Dist: datasets
Requires-Dist: langchain
Requires-Dist: langchain_community
Requires-Dist: langchain-google-genai
Requires-Dist: langchain-openai
Requires-Dist: langchain_ollama
Requires-Dist: langgraph
Requires-Dist: langgraph-supervisor
Requires-Dist: lxml
Requires-Dist: beautifulsoup4
Requires-Dist: gradio
Requires-Dist: pyperclip
Requires-Dist: fastmcp
Requires-Dist: docker
Requires-Dist: pdf-to-markdown
Provides-Extra: dev
Requires-Dist: pytest; extra == "dev"
Requires-Dist: pytest-cov; extra == "dev"
Dynamic: license-file
